nxpy_ccase-1.0.0-py3.7-nspkg.pth
nxpy/ccase/__init__.py
nxpy/ccase/cleartool.py
nxpy_ccase-1.0.0.dist-info/LICENSE.txt
nxpy_ccase-1.0.0.dist-info/METADATA
nxpy_ccase-1.0.0.dist-info/WHEEL
nxpy_ccase-1.0.0.dist-info/namespace_packages.txt
nxpy_ccase-1.0.0.dist-info/top_level.txt
nxpy_ccase-1.0.0.dist-info/RECORD
